Metadata-Version: 1.1
Name: random-publication-test
Version: 0.0.4
Summary: Project Description
Home-page: UNKNOWN
Author: james saunders <james@businessoptics.biz>
Author-email: UNKNOWN
License: MIT
Platform: UNKNOWN
Classifier: Framework :: Dash
